tests/__init__.py
tests/conftest.py
tests/requirements-test.txt.py
tests/test_client.py
tests/test_engine.py
tests/test_singleton.py
tests/test_versioning.py
tests/utils.py
tests/abstracts/__init__.py
tests/abstracts/test_job.py
tests/abstracts/test_task.py
tests/abstracts/test_workflow.py
tests/fixtures/__init__.py
tests/fixtures/fixture_builder.py
tests/fixtures/fixture_client.py
tests/fixtures/fixture_engine.py
tests/fixtures/fixture_event.py
tests/fixtures/fixture_properties.py
tests/fixtures/fixture_serializer.py
tests/fixtures/fixture_task.py
tests/fixtures/fixture_wait.py
tests/fixtures/fixture_workflow.py
tests/fixtures/fixtures.py
tests/query/__init__.py
tests/query/test_builder.py
tests/services/__init__.py
tests/services/test_properties.py
tests/services/test_serializer.py
tests/tasks/__init__.py
tests/tasks/test_wait.py
tests/traits/__init__.py
tests/traits/test_with_duration.py
tests/traits/test_with_timestamp.py
zenaton/__init__.py
zenaton/client.py
zenaton/engine.py
zenaton/exceptions.py
zenaton/parallel.py
zenaton/processor.py
zenaton/singleton.py
zenaton/abstracts/__init__.py
zenaton/abstracts/event.py
zenaton/abstracts/job.py
zenaton/abstracts/task.py
zenaton/abstracts/workflow.py
zenaton/contexts/__init__.py
zenaton/contexts/task_context.py
zenaton/contexts/workflow_context.py
zenaton/query/__init__.py
zenaton/query/builder.py
zenaton/services/__init__.py
zenaton/services/graphql_service.py
zenaton/services/http_service.py
zenaton/services/properties.py
zenaton/services/serializer.py
zenaton/tasks/__init__.py
zenaton/tasks/wait.py
zenaton/traits/__init__.py
zenaton/traits/with_duration.py
zenaton/traits/with_timestamp.py
zenaton/traits/zenatonable.py
zenaton/workflows/__init__.py
zenaton/workflows/version.py
zenaton-0.4.2.dist-info/LICENSE.txt
zenaton-0.4.2.dist-info/METADATA
zenaton-0.4.2.dist-info/WHEEL
zenaton-0.4.2.dist-info/top_level.txt
zenaton-0.4.2.dist-info/RECORD
