Metadata-Version: 2.1
Name: zenaton
Version: 0.4.2
Summary: Zenaton client library
Home-page: https://zenaton.com/
Author: Zenaton
Author-email: yann@zenaton.com
License: Apache License, Version 2.0
Keywords: workflow engine,workflows,orchestration,event-driven architecture,queuing systems,orchestration engine,background jobs,hosted queues,queues,jobs,asynchronous tasks
Platform: UNKNOWN
Classifier: Development Status :: 4 - Beta
Classifier: Intended Audience :: Developers
Classifier: Intended Audience :: System Administrators
Classifier: License :: OSI Approved :: Apache Software License
Classifier: Programming Language :: Python :: 3.5
Classifier: Topic :: Software Development :: Libraries
Requires-Python: >=3
Requires-Dist: requests
Requires-Dist: pytz
Provides-Extra: test
Requires-Dist: freezegun ; extra == 'test'
Requires-Dist: pytest ; extra == 'test'
Requires-Dist: pytest-mock ; extra == 'test'
Requires-Dist: python-dotenv ; extra == 'test'
